thiruthathari/bktree.py
thiruthathari/bloom.py
thiruthathari/resources.py
thiruthathari/setup.py
thiruthathari/thiruthi.py
thiruthathari/trie.py
thiruthathari/utils.py
thiruthathari-0.0.1.dist-info/LICENSE
thiruthathari-0.0.1.dist-info/METADATA
thiruthathari-0.0.1.dist-info/WHEEL
thiruthathari-0.0.1.dist-info/top_level.txt
thiruthathari-0.0.1.dist-info/RECORD
