Metadata-Version: 2.1
Name: thiruthathari
Version: 0.0.1
Summary: a tower of spellcheckers for Tamil
Author-email: vanangamudi <selva.developer@gmail.com>
License: GNU GENERAL PUBLIC LICENSE
Project-URL: Homepage, https://github.com/vanangamudi/thiruthathari
Project-URL: Bug Tracker, https://github.com/vanangamudi/thiruthathari/issues
Classifier: Programming Language :: Python :: 3
Classifier: Operating System :: OS Independent
Requires-Python: >=3.5
License-File: LICENSE
Requires-Dist: bloom-filter (==1.3.3)
Requires-Dist: editdistance (==0.6.0)
Requires-Dist: Levenshtein (==0.20.1)
Requires-Dist: Open-Tamil (==1.1)
